nbs_core/__init__.py
nbs_core/autoconf.py
nbs_core/autoload.py
nbs_core/beamline.py
nbs_core/utils.py
nbs_core-0.1.0.dist-info/METADATA
nbs_core-0.1.0.dist-info/WHEEL
nbs_core-0.1.0.dist-info/licenses/LICENSE
nbs_core-0.1.0.dist-info/RECORD
