Metadata-Version: 2.4
Name: nbs-core
Version: 0.1.0
Summary: NBS Core Utilities
Project-URL: homepage, https://github.com/xraygui/nbs-core
Author-email: Charles Titus <ctitus@bnl.gov>
License-File: LICENSE
Keywords: beamline,bluesky,nsls-ii
Classifier: Intended Audience :: Science/Research
Classifier: License :: Public Domain
Classifier: Operating System :: OS Independent
Classifier: Programming Language :: Python :: 3
Requires-Python: >=3.9
Requires-Dist: tomli; python_version < '3.11'
